headliner/__init__.py
headliner/attention_plot.py
headliner/clean_training_runner.py
headliner/embeddings.py
headliner/losses.py
headliner/prediction.py
headliner/prediction_runner.py
headliner/trainer.py
headliner/training.py
headliner/training_runner.py
headliner/training_runner_test.py
headliner/callbacks/__init__.py
headliner/callbacks/evaluation_callback.py
headliner/callbacks/model_checkpoint_callback.py
headliner/callbacks/tensorboard_callback.py
headliner/callbacks/validation_callback.py
headliner/evaluation/__init__.py
headliner/evaluation/bleu_scorer.py
headliner/evaluation/scorer.py
headliner/model/__init__.py
headliner/model/attention_model.py
headliner/model/attention_summarizer.py
headliner/model/basic_model.py
headliner/model/basic_summarizer.py
headliner/model/bert_model.py
headliner/model/bert_summarizer.py
headliner/model/model_attention.py
headliner/model/model_basic.py
headliner/model/model_bert.py
headliner/model/model_transformer.py
headliner/model/summarizer.py
headliner/model/summarizer_attention.py
headliner/model/summarizer_basic.py
headliner/model/summarizer_bert.py
headliner/model/summarizer_transformer.py
headliner/model/transformer_model.py
headliner/model/transformer_summarizer.py
headliner/model/transformer_util.py
headliner/preprocessing/__init__.py
headliner/preprocessing/bert_preprocessor.py
headliner/preprocessing/bert_vectorizer.py
headliner/preprocessing/bucket_generator.py
headliner/preprocessing/dataset_generator.py
headliner/preprocessing/keras_tokenizer.py
headliner/preprocessing/preprocessor.py
headliner/preprocessing/tokenizer.py
headliner/preprocessing/vectorizer.py
headliner/utils/__init__.py
headliner/utils/logger.py
tests/callbacks/__init__.py
tests/callbacks/test_evaluation_callback.py
tests/callbacks/test_model_checkpointing_callback.py
tests/callbacks/test_validation_callback.py
tests/evaluation/__init__.py
tests/evaluation/test_bleu_scorer.py
tests/model/__init__.py
tests/model/test_summarizer.py
headliner-1.0.2.dist-info/LICENSE
headliner-1.0.2.dist-info/METADATA
headliner-1.0.2.dist-info/WHEEL
headliner-1.0.2.dist-info/top_level.txt
headliner-1.0.2.dist-info/RECORD
