Metadata-Version: 2.1
Name: headliner
Version: 1.0.2
Summary: Easy training and deployment of seq2seq models.
Home-page: UNKNOWN
Author: Christian Schäfer
Author-email: c.schaefer.home@gmail.com
License: MIT
Platform: UNKNOWN
Classifier: Development Status :: 4 - Beta
Classifier: Intended Audience :: Developers
Classifier: Intended Audience :: Education
Classifier: Intended Audience :: Science/Research
Classifier: License :: OSI Approved :: MIT License
Classifier: Operating System :: POSIX :: Linux
Classifier: Operating System :: MacOS :: MacOS X
Classifier: Operating System :: Microsoft :: Windows
Classifier: Programming Language :: Python :: 3
Classifier: Programming Language :: Python :: 3.6
Classifier: Programming Language :: Python :: 3.7
Classifier: Topic :: Scientific/Engineering
Classifier: Topic :: Software Development :: Libraries
Classifier: Topic :: Software Development :: Libraries :: Python Modules
Requires-Dist: scikit-learn
Requires-Dist: nltk
Requires-Dist: pyyaml
Requires-Dist: transformers (>=2.2.2)
Requires-Dist: spacy (>=2.2.2)
Provides-Extra: dev
Requires-Dist: bumpversion ; extra == 'dev'
Provides-Extra: docs
Requires-Dist: mkdocs ; extra == 'docs'
Requires-Dist: mkdocs-material ; extra == 'docs'
Provides-Extra: tests
Requires-Dist: pytest ; extra == 'tests'
Requires-Dist: pytest-cov ; extra == 'tests'
Requires-Dist: codecov ; extra == 'tests'
Requires-Dist: tensorflow (==2.0.0) ; extra == 'tests'
